picta/__init__.py
picta/loader.py
picta/render.py
picta/icons/arrow-left.svg
picta/icons/arrow-right.svg
picta/icons/battery.svg
picta/icons/bell.svg
picta/icons/bolt.svg
picta/icons/book.svg
picta/icons/calendar-check.svg
picta/icons/calendar.svg
picta/icons/camera.svg
picta/icons/check.svg
picta/icons/chevron-down.svg
picta/icons/chevron-left.svg
picta/icons/chevron-right.svg
picta/icons/chevron-up.svg
picta/icons/chevrons-down.svg
picta/icons/chevrons-left.svg
picta/icons/chevrons-right.svg
picta/icons/chevrons-up.svg
picta/icons/clipboard.svg
picta/icons/clock.svg
picta/icons/cloud.svg
picta/icons/credit-card.svg
picta/icons/download.svg
picta/icons/eye-off.svg
picta/icons/eye.svg
picta/icons/file.svg
picta/icons/folder-minus.svg
picta/icons/folder-open.svg
picta/icons/folder-plus.svg
picta/icons/folder.svg
picta/icons/forward.svg
picta/icons/globe.svg
picta/icons/hash.svg
picta/icons/heart.svg
picta/icons/key.svg
picta/icons/layers.svg
picta/icons/life-buoy.svg
picta/icons/link.svg
picta/icons/loader.svg
picta/icons/lock-open.svg
picta/icons/lock.svg
picta/icons/log-in.svg
picta/icons/log-out.svg
picta/icons/mail.svg
picta/icons/map.svg
picta/icons/maximize-2.svg
picta/icons/maximize.svg
picta/icons/menu.svg
picta/icons/message-circle.svg
picta/icons/message-square.svg
picta/icons/mic.svg
picta/icons/minimize-2.svg
picta/icons/minimize.svg
picta/icons/monitor.svg
picta/icons/moon.svg
picta/icons/music.svg
picta/icons/pause.svg
picta/icons/phone.svg
picta/icons/play.svg
picta/icons/plus.svg
picta/icons/repeat.svg
picta/icons/rotate-ccw.svg
picta/icons/rotate-cw.svg
picta/icons/save.svg
picta/icons/search.svg
picta/icons/settings.svg
picta/icons/share.svg
picta/icons/smile.svg
picta/icons/star.svg
picta/icons/sun.svg
picta/icons/tag.svg
picta/icons/trash.svg
picta/icons/trophy.svg
picta/icons/unlink.svg
picta/icons/upload.svg
picta/icons/user-minus.svg
picta/icons/user-plus.svg
picta/icons/user.svg
picta/icons/video.svg
picta/icons/wifi.svg
picta-0.1.0.dist-info/licenses/LICENSE
picta-0.1.0.dist-info/METADATA
picta-0.1.0.dist-info/WHEEL
picta-0.1.0.dist-info/top_level.txt
picta-0.1.0.dist-info/RECORD
