Metadata-Version: 2.4
Name: picta
Version: 0.1.0
Summary: Picta is a Python-first, dependency-free icon library inspired by Lucide Icons. It allows Python developers to easily use SVG icons in web apps, dashboards, or any Python project that can render HTML.
Author: Vaibhav Rawat
Requires-Python: >=3.8
License-File: LICENSE
Dynamic: author
Dynamic: license-file
Dynamic: requires-python
Dynamic: summary
